ragcore/__init__.py
ragcore/cli.py
ragcore/version.py
ragcore/api/__init__.py
ragcore/api/client.py
ragcore/app/__init__.py
ragcore/app/base_app.py
ragcore/dto/__init__.py
ragcore/dto/document_dto.py
ragcore/models/__init__.py
ragcore/models/app_model.py
ragcore/models/config_model.py
ragcore/models/database_model.py
ragcore/models/document_loader_model.py
ragcore/models/document_model.py
ragcore/models/embedding_model.py
ragcore/models/llm_model.py
ragcore/models/prompt_model.py
ragcore/services/__init__.py
ragcore/services/database_service.py
ragcore/services/document_service.py
ragcore/services/llm_service.py
ragcore/services/text_splitter_service.py
ragcore/shared/__init__.py
ragcore/shared/constants.py
ragcore/shared/errors.py
ragcore/shared/utils.py
ragcore-1.0.4.dist-info/LICENSE
ragcore-1.0.4.dist-info/METADATA
ragcore-1.0.4.dist-info/WHEEL
ragcore-1.0.4.dist-info/entry_points.txt
ragcore-1.0.4.dist-info/top_level.txt
ragcore-1.0.4.dist-info/RECORD
