Metadata-Version: 2.1
Name: ragcore
Version: 1.0.4
Summary: A library to build Retrieval-Augmented Generation applications with only a few lines of code.
Home-page: https://github.com/daved01/ragcore
Author: David Kirchhoff
Author-email: david.kirchhoff@mail.utoronto.ca
Project-URL: Bug Reports, https://github.com/daved01/ragcore/issues
Project-URL: Funding, https://github.com/sponsors/daved01
Project-URL: Say Thanks!, https://www.paypal.com/donate/?hosted_button_id=JH7HXP6VE5U3S
Project-URL: Source, https://github.com/daved01/ragcore
Project-URL: Documentation, https://daved01.github.io/ragcore/
Keywords: retrieval augmented generation,rag,development,artificial intelligence,large language models
Classifier: Development Status :: 3 - Alpha
Classifier: Intended Audience :: Developers
Classifier: Topic :: Software Development :: Libraries
Classifier: Topic :: Scientific/Engineering :: Artificial Intelligence
Classifier: License :: OSI Approved :: MIT License
Classifier: Programming Language :: Python :: 3
Classifier: Programming Language :: Python :: 3.10
Classifier: Programming Language :: Python :: 3.11
Classifier: Programming Language :: Python :: 3 :: Only
Requires-Python: >=3.10, <4
License-File: LICENSE
Requires-Dist: aiofiles ==23.1.0
Requires-Dist: chromadb ==0.4.22
Requires-Dist: Jinja2 ==3.1.3
Requires-Dist: langchain ==0.1.1
Requires-Dist: langchain-community ==0.0.13
Requires-Dist: openai ==1.7.2
Requires-Dist: pinecone-client ==3.0.3
Requires-Dist: pypdf ==3.17.0
Requires-Dist: tiktoken ==0.4.0
